bayfox/__init__.py
bayfox/plot.py
bayfox/predict.py
bayfox/utils.py
bayfox/example_data/VM21-30.csv
bayfox/modelparams/__init__.py
bayfox/modelparams/core.py
bayfox/modelparams/tracedumps/annual_hierarchical_trace.csv
bayfox/modelparams/tracedumps/annual_pooled_trace.csv
bayfox/modelparams/tracedumps/seasonal_hierarchical_trace.csv
bayfox/tests/__init__.py
bayfox/tests/test_modelparams_drawsdispenser.py
bayfox/tests/test_predict_d18oc.py
bayfox/tests/test_predict_seatemp.py
bayfox/tests/test_prediction.py
bayfox-0.0.1a3.dist-info/METADATA
bayfox-0.0.1a3.dist-info/RECORD
bayfox-0.0.1a3.dist-info/WHEEL
bayfox-0.0.1a3.dist-info/top_level.txt
