Metadata-Version: 2.1
Name: bayfox
Version: 0.0.1a3
Summary: Experimental Bayesian planktic foraminifera calibration, for Python.
Home-page: https://github.com/brews/bayfox
Author: S. Brewster Malevich
Author-email: malevich@email.arizona.edu
License: GPLv3
Keywords: marine paleoclimate paleoceanography d18o δ18o
Platform: UNKNOWN
Classifier: Development Status :: 3 - Alpha
Classifier: Intended Audience :: Developers
Classifier: Intended Audience :: Science/Research
Classifier: Topic :: Scientific/Engineering
Classifier: License :: OSI Approved :: GNU General Public License v3 or later (GPLv3+)
Classifier: Programming Language :: Python :: 3
Requires-Dist: numpy
Requires-Dist: matplotlib
Requires-Dist: attrs
